[
    {
        "filename": "index.html",
        "attr": {
            "data-transition": "linear"
        }
    },
    "me.md",
    [
        "work-experience.md",
        "skills.md",
        "attend.com.md",
        "attend-example.md",
        "bike-beacon.md",
        "northeastern.md"
    ],
    [
        "gallery.md",
        "html5-space-invaders.html",
        "pokemon-safari.md",
        {
            "filename": "mandel.md",
            "attr": {
                "data-background": "slides/images/mandel.png"
            }
        },
        "st-petersburg.md",
        "go-solution.md"
    ],
    [
        "contact.md"
    ]
]